{
	"name": "Apathetic Ocean",
	"type": "dark",
	"semanticHighlighting": true,
	"colors": {
		"editor.background": "#0e0e15",
		"editor.foreground": "#8e93b0c2",
		"editor.hoverHighlightBackground": "#1b162994",
		"editor.selectionHighlightBorder": "#1b162994",
		"list.highlightForeground": "#ffcb6b",
		"editor.selectionBackground": "#2d22476b",
		"editor.selectionHighlightBackground": "#39324952",
		"editor.inactiveSelectionBackground": "#2d22473d",
		"editor.findMatchBackground": "#2a2540dc",
		"editor.findMatchHighlightBackground": "#18142ddc",
		"editor.findRangeHighlightBackground": "#39324952",
		"diffEditorGutter.insertedLineBackground": "#0a2b20ff",
		"diffEditorGutter.removedLineBackground": "#2c0c15ff",
		"editorGutter.modifiedBackground": "#e9c162c0",
		"editorGutter.addedBackground": "#0a2b20ff",
		"editorGutter.deletedBackground": "#2c0c15ff",
		"quickInput.background": "#0f0f12",
		"quickInput.foreground": "#a7a4af",
		"quickInputList.focusBackground": "#1c1e29cc",
		"quickInputList.focusForeground": "#e1e2e5",
		"list.hoverBackground": "#1c1e29cc",
		"list.hoverForeground": "#e1e2e5",
		"quickInput.list.focusBackground": "#1c1e29cc",
		"activityBar.background": "#0f0f12",
		"activityBar.foreground": "#96a5b6",
		"activityBar.inactiveForeground": "#45414C",
		"activityBar.border": "#0f0f12",
		"activityBarBadge.background": "#FF7A0000",
		"activityBarBadge.foreground": "#C3E88D",
		"sideBar.background": "#0f0f12",
		"sideBar.foreground": "#827b90cf",
		"sideBar.border": "#0f0f12",
		"sideBarSectionHeader.background": "#0f0e1000",
		"sideBarSectionHeader.foreground": "#e3e1e8b7",
		"panel.border": "#a099ae14",
		"sash.hoverBorder": "#182356",
		"editorGroup.border": "#212131",
		"editor.compositionBorder": "#182356",
		"editorWidget.background": "#1c1e29cc",
		"editorWidget.border": "#a099ae14",
		"editorWidget.foreground": "#a7a4af",
		"input.border": "#26242a99",
		"panel.background": "#0f0f12",
		"panelTitle.activeForeground": "#96a5b6",
		"panelTitle.inactiveForeground": "#E0E0E0",
		"panelTitle.activeBorder": "#ffffff",
		"titleBar.activeBackground": "#0e0e15",
		"titleBar.activeForeground": "#a7a4af",
		"titleBar.inactiveBackground": "#0e0e15",
		"titleBar.inactiveForeground": "#827b90cf",
		"statusBar.background": "#0f0f12",
		"statusBar.foreground": "#5f6384b8",
		"statusBar.border": "#ffffff00",
		"statusBar.noFolderBackground": "#0B0915",
		"statusBar.noFolderForeground": "#4D4A56",
		"tab.activeBackground": "#0f0e10",
		"tab.activeForeground": "#96a5b6",
		"tab.activeBorder": "#d0cfd3",
		"tab.activeBorderTop": "#d0cfd3",
		"tab.inactiveBackground": "#0f0f12",
		"tab.inactiveForeground": "#B5B5B5",
		"tab.hoverBackground": "#0f0e10",
		"tab.hoverForeground": "#e1e2e5",
		"tab.unfocusedActiveBackground": "#0f0e10",
		"tab.unfocusedActiveForeground": "#4D4A56",
		"tab.lastPinnedBorder": "#ffcb6b",
		"list.activeSelectionBackground": "#2A2441",
		"list.activeSelectionForeground": "#E6E2D1",
		"list.inactiveSelectionBackground": "#1B1629",
		"list.inactiveSelectionForeground": "#E6E2D1",
		"list.focusBackground": "#2A2441",
		"list.focusForeground": "#E6E2D1",
		"input.background": "#14141b",
		"input.foreground": "#ffffff99",
		"input.placeholderForeground": "#b5b5b545",
		"button.background": "#7a5acd2e",
		"button.foreground": "#80ffecba",
		"button.hoverBackground": "#8d61ff2e",
		"button.secondaryBackground": "#17161e54",
		"button.secondaryForeground": "#d0d5dbba",
		"button.secondaryHoverBackground": "#2b293754",
		"dropdown.background": "#1B1629",
		"dropdown.foreground": "#E6E2D1",
		"dropdown.border": "#45414C",
		"dropdown.listBackground": "#1B1629",
		"badge.background": "#0b0b19c9",
		"badge.foreground": "#82aaffd4",
		"scrollbar.shadow": "#00000080",
		"scrollbarSlider.background": "#45414C40",
		"scrollbarSlider.hoverBackground": "#45414C80",
		"scrollbarSlider.activeBackground": "#45414C",
		"minimap.background": "#0e0e15",
		"minimap.selectionHighlight": "#2d22476b",
		"minimap.errorHighlight": "#b70b24",
		"minimap.warningHighlight": "#E6986B",
		"minimap.findMatchHighlight": "#2a2540dc",
		"breadcrumb.background": "#0e0e15",
		"breadcrumb.foreground": "default",
		"breadcrumb.focusForeground": "#E6E2D1",
		"breadcrumb.activeSelectionForeground": "#FFCB6B",
		"terminal.background": "#0f0d12",
		"terminal.foreground": "#626274",
		"terminal.border": "#a099ae14",
		"terminalCursor.foreground": "#e1e2e5",
		"terminal.selectionBackground": "#2d22476b",
		"terminal.ansiBlack": "#2A273F",
		"terminal.ansiRed": "#ff00af",
		"terminal.ansiGreen": "#C3E88D",
		"terminal.ansiYellow": "#FFCB6B",
		"terminal.ansiBlue": "#ac82ff",
		"terminal.ansiMagenta": "#C792EA",
		"terminal.ansiCyan": "#80d3c4",
		"terminal.ansiWhite": "#D1D3D9",
		"terminal.ansiBrightBlack": "#3F3B5A",
		"terminal.ansiBrightRed": "#FF6B82",
		"terminal.ansiBrightGreen": "#D7F2A6",
		"terminal.ansiBrightYellow": "#FFE082",
		"terminal.ansiBrightBlue": "#9EC3FF",
		"terminal.ansiBrightMagenta": "#DDA4FF",
		"terminal.ansiBrightCyan": "#A3EEFF",
		"terminal.ansiBrightWhite": "#FFFFFF",
		"notifications.background": "#1c1e29cc",
		"notifications.foreground": "#e1e2e5",
		"notifications.border": "#45414C",
		"peekViewEditor.background": "#0F0D1A",
		"peekView.border": "#45414C",
		"peekViewResult.background": "#1B1629",
		"peekViewResult.selectionBackground": "#2A2441",
		"peekViewTitle.background": "#0B0915",
		"peekViewTitleLabel.foreground": "#E6E2D1",
		"diffEditor.insertedTextBackground": "#061611d9",
		"diffEditor.removedTextBackground": "#290011cc",
		"diffEditor.insertedLineBackground": "#091511",
		"diffEditor.removedLineBackground": "#12080b",
		"diffEditor.diagonalFill": "#45414C",
		"editorInlayHint.insertedTextBackground": "#061611d9",
		"editorInlayHint.removedTextBackground": "#290011cc",
		"editorInlayHint.insertedLineBackground": "#091511",
		"editorInlayHint.removedLineBackground": "#12080b",
		"editorInlayHint.diagonalFill": "#45414C",
		"merge.currentHeaderBackground": "#1B1629",
		"merge.currentContentBackground": "#34727E",
		"merge.incomingHeaderBackground": "#1B1629",
		"merge.incomingContentBackground": "#B79251",
		"merge.commonHeaderBackground": "#1B1629",
		"merge.commonContentBackground": "#35323B",
		"editorSuggestWidget.background": "#1B1629",
		"editorIndentGuide.background1": "#29192969",
		"editorIndentGuide.activeBackground1": "#6b406b69",
		"editorWhitespace.foreground": "#272636",
		"editorRuler.foreground": "#29192969",
		"editorLineNumber.foreground": "#383d51",
		"editorLineNumber.activeForeground": "#a7a4af",
		"editorHoverWidget.background": "#1c1e29cc",
		"editorHoverWidget.border": "#527bb254",
		"editorHoverWidget.foreground": "#d4edff99",
		"sideBarTitle.background": "#0f0f12",
		"sideBarTitle.foreground": "#a7a4af",
		"tab.border": "#212131",
		"editorGroupHeader.tabsBackground": "#0f0f12",
		"button.border": "#212131",
		"button.separator": "#161621",
		"tree.indentGuidesStroke": "#212131",
		"composerPane.background": "#0f0f12",
		"gitDecoration.addedResourceForeground": "#449dab",
		"gitDecoration.modifiedResourceForeground": "#6183bb",
		"gitDecoration.deletedResourceForeground": "#914c54",
		"gitDecoration.untrackedResourceForeground": "#449dab",
		"gitDecoration.ignoredResourceForeground": "#515670",
		"gitDecoration.conflictingResourceForeground": "#e46876",
		"gitDecoration.renamedResourceForeground": "#449dab",
		"gitDecoration.stageModifiedResourceForeground": "#6183bb",
		"gitDecoration.stageDeletedResourceForeground": "#914c54",
		"gitDecoration.submoduleResourceForeground": "#827b90cf",
		"editorCursor.foreground": "#e1e2e5",
		"window.activeBorder": "#a099ae14",
		"window.inactiveBorder": "#212131",
		"icon.foreground": "#827b90cf",
		"focusBorder": "#33b3cc",
		"contrastBorder": "#212131",
		"menu.background": "#151520",
		"menu.foreground": "#a7a4af",
		"menu.selectionBackground": "#2d22476b",
		"menu.selectionForeground": "#a7a4af",
		"menu.separatorBackground": "#161621",
		"editorSuggestWidget.border": "#527bb254",
		"editorSuggestWidget.foreground": "#d4edff99",
		"editorSuggestWidget.selectedBackground": "#2d22476b",
		"progressBar.background": "#33b3cc",
		"debugConsole.infoForeground": "#78DCE8",
		"debugConsole.warningForeground": "#ffcb6b",
		"debugConsole.errorForeground": "#FF6188",
		"debugConsole.sourceForeground": "#a7a4af",
		"textLink.foreground": "#33b3cc",
		"textLink.activeForeground": "#33b3cc",
		"textPreformat.background": "#151520",
		"textPreformat.foreground": "#a7a4af",
		"textSeparator.foreground": "#161621",
		"editorError.background": "#B70B24",
		"list.errorForeground": "#943c4c",
		"peekViewEditor.matchHighlightBackground": "#2d22476b",
		"peekViewResult.matchHighlightBackground": "#2d22476b",
		"peekViewTitleDescription.foreground": "#827b90cf",
		"editorError.foreground": "#FF6188",
		"editorWarning.foreground": "#ffcb6b",
		"editorInfo.foreground": "#78DCE8",
		"terminal.dropBackground": "#151520",
		"foreground": "#a7a4af"
	},
	"tokenColors": [
		{
			"name": "source",
			"scope": [
				"source"
			],
			"settings": {
				"foreground": "#a7a4af"
			}
		},
		{
			"name": "text",
			"scope": [
				"text"
			],
			"settings": {
				"foreground": "#a7a4af"
			}
		},
		{
			"name": "comment",
			"scope": [
				"comment"
			],
			"settings": {
				"foreground": "#383d51",
				"fontStyle": "italic"
			}
		},
		{
			"name": "punctuation.definition.comment",
			"scope": [
				"punctuation.definition.comment"
			],
			"settings": {
				"foreground": "#383d51",
				"fontStyle": "italic"
			}
		},
		{
			"name": "string",
			"scope": [
				"string"
			],
			"settings": {
				"foreground": "#95c17b"
			}
		},
		{
			"name": "string.regexp",
			"scope": [
				"string.regexp"
			],
			"settings": {
				"foreground": "#FF6188",
				"fontStyle": "italic"
			}
		},
		{
			"name": "constant.character.escape",
			"scope": [
				"constant.character.escape"
			],
			"settings": {
				"foreground": "#95c17b"
			}
		},
		{
			"name": "constant.other.placeholder",
			"scope": [
				"constant.other.placeholder"
			],
			"settings": {
				"foreground": "#95c17b"
			}
		},
		{
			"name": "separator.border",
			"scope": [
				"separator.border"
			],
			"settings": {
				"foreground": "#161621"
			}
		},
		{
			"name": "focusBorder",
			"scope": [
				"focusBorder"
			],
			"settings": {
				"foreground": "#182356"
			}
		},
		{
			"name": "gauge.border",
			"scope": [
				"gauge.border"
			],
			"settings": {
				"foreground": "#a099ae14"
			}
		},
		{
			"name": "sash.hoverBorder",
			"scope": [
				"sash.hoverBorder"
			],
			"settings": {
				"foreground": "#182356"
			}
		},
		{
			"name": "editorGroup.border",
			"scope": [
				"editorGroup.border"
			],
			"settings": {
				"foreground": "#212131"
			}
		},
		{
			"name": "punctuation.definition.template-expression",
			"scope": [
				"punctuation.definition.template-expression"
			],
			"settings": {
				"foreground": "#95c17b"
			}
		},
		{
			"name": "meta.template.expression",
			"scope": [
				"meta.template.expression"
			],
			"settings": {
				"foreground": "#95c17b"
			}
		},
		{
			"name": "constant",
			"scope": [
				"constant"
			],
			"settings": {
				"foreground": "#33b3cc"
			}
		},
		{
			"name": "constant.numeric",
			"scope": [
				"constant.numeric"
			],
			"settings": {
				"foreground": "#33b3cc"
			}
		},
		{
			"name": "constant.language",
			"scope": [
				"constant.language"
			],
			"settings": {
				"foreground": "#33b3cc"
			}
		},
		{
			"name": "quickInput.background",
			"scope": [
				"quickInput.background"
			],
			"settings": {
				"foreground": "#0f0f12"
			}
		},
		{
			"name": "quickInput.foreground",
			"scope": [
				"quickInput.foreground"
			],
			"settings": {
				"foreground": "#a7a4af"
			}
		},
		{
			"name": "quickInput.focusBackground",
			"scope": [
				"quickInput.focusBackground"
			],
			"settings": {
				"foreground": "#0f0f12"
			}
		},
		{
			"name": "quickInput.focusForeground",
			"scope": [
				"quickInput.focusForeground"
			],
			"settings": {
				"foreground": "#a7a4af"
			}
		},
		{
			"name": "quickInputList.background",
			"scope": [
				"quickInputList.background"
			],
			"settings": {
				"foreground": "#0f0f12"
			}
		},
		{
			"name": "quickInputList.foreground",
			"scope": [
				"quickInputList.foreground"
			],
			"settings": {
				"foreground": "#a7a4af"
			}
		},
		{
			"name": "quickInputList.focusBackground",
			"scope": [
				"quickInputList.focusBackground"
			],
			"settings": {
				"foreground": "#0f0f12"
			}
		},
		{
			"name": "quickInputList.focusForeground",
			"scope": [
				"quickInputList.focusForeground"
			],
			"settings": {
				"foreground": "#a7a4af"
			}
		},
		{
			"name": "list.hoverBackground",
			"scope": [
				"list.hoverBackground"
			],
			"settings": {
				"foreground": "#1c1e29cc"
			}
		},
		{
			"name": "list.hoverForeground",
			"scope": [
				"list.hoverForeground"
			],
			"settings": {
				"foreground": "#a7a4af"
			}
		},
		{
			"name": "keyword",
			"scope": [
				"keyword"
			],
			"settings": {
				"foreground": "#afd1e9cf"
			}
		},
		{
			"name": "keyword.control",
			"scope": [
				"keyword.control"
			],
			"settings": {
				"foreground": "#e3e1e8a8"
			}
		},
		{
			"name": "keyword.control.conditional",
			"scope": [
				"keyword.control.conditional"
			],
			"settings": {
				"foreground": "#e3e1e8a8"
			}
		},
		{
			"name": "keyword.control.loop",
			"scope": [
				"keyword.control.loop"
			],
			"settings": {
				"foreground": "#e3e1e8a8"
			}
		},
		{
			"name": "keyword.control.flow",
			"scope": [
				"keyword.control.flow"
			],
			"settings": {
				"foreground": "#e3e1e8a8"
			}
		},
		{
			"name": "keyword.control.import",
			"scope": [
				"keyword.control.import"
			],
			"settings": {
				"foreground": "#d09bd2"
			}
		},
		{
			"name": "keyword.control.export",
			"scope": [
				"keyword.control.export"
			],
			"settings": {
				"foreground": "#d09bd2"
			}
		},
		{
			"name": "keyword.operator",
			"scope": [
				"keyword.operator"
			],
			"settings": {
				"foreground": "#E60063"
			}
		},
		{
			"name": "keyword.operator.logical",
			"scope": [
				"keyword.operator.logical"
			],
			"settings": {
				"foreground": "#E60063"
			}
		},
		{
			"name": "keyword.operator.assignment",
			"scope": [
				"keyword.operator.assignment"
			],
			"settings": {
				"foreground": "#E60063"
			}
		},
		{
			"name": "keyword.operator.arithmetic",
			"scope": [
				"keyword.operator.arithmetic"
			],
			"settings": {
				"foreground": "#E60063"
			}
		},
		{
			"name": "keyword.operator.comparison",
			"scope": [
				"keyword.operator.comparison"
			],
			"settings": {
				"foreground": "#E60063"
			}
		},
		{
			"name": "keyword.operator.wordlike",
			"scope": [
				"keyword.operator.wordlike"
			],
			"settings": {
				"foreground": "#E60063"
			}
		},
		{
			"name": "storage",
			"scope": [
				"storage"
			],
			"settings": {
				"foreground": "#5b6467"
			}
		},
		{
			"name": "storage.type",
			"scope": [
				"storage.type"
			],
			"settings": {
				"foreground": "#5b6467"
			}
		},
		{
			"name": "storage.type.function",
			"scope": [
				"storage.type.function"
			],
			"settings": {
				"foreground": "#7d7a8b"
			}
		},
		{
			"name": "storage.type.class",
			"scope": [
				"storage.type.class"
			],
			"settings": {
				"foreground": "#7d7a8b"
			}
		},
		{
			"name": "storage.modifier",
			"scope": [
				"storage.modifier"
			],
			"settings": {
				"foreground": "#5b6467"
			}
		},
		{
			"name": "storage.type.primitive",
			"scope": [
				"storage.type.primitive"
			],
			"settings": {
				"foreground": "#e0a2d3"
			}
		},
		{
			"name": "variable",
			"scope": [
				"variable"
			],
			"settings": {
				"foreground": "#e3e1e8c7"
			}
		},
		{
			"name": "variable.other",
			"scope": [
				"variable.other"
			],
			"settings": {
				"foreground": "#96a5b6"
			}
		},
		{
			"name": "variable.parameter",
			"scope": [
				"variable.parameter"
			],
			"settings": {
				"foreground": "#8e8db3",
				"fontStyle": "italic"
			}
		},
		{
			"name": "variable.language",
			"scope": [
				"variable.language"
			],
			"settings": {
				"foreground": "#ffa114",
				"fontStyle": "italic"
			}
		},
		{
			"name": "variable.language.this",
			"scope": [
				"variable.language.this"
			],
			"settings": {
				"foreground": "#ffa114",
				"fontStyle": "italic"
			}
		},
		{
			"name": "variable.language.super",
			"scope": [
				"variable.language.super"
			],
			"settings": {
				"foreground": "#ffa114",
				"fontStyle": "italic"
			}
		},
		{
			"name": "entity.name.function",
			"scope": [
				"entity.name.function"
			],
			"settings": {
				"foreground": "#f5e0dc"
			}
		},
		{
			"name": "support.function",
			"scope": [
				"support.function"
			],
			"settings": {
				"foreground": "#95d4ca"
			}
		},
		{
			"name": "meta.function-call.generic",
			"scope": [
				"meta.function-call.generic"
			],
			"settings": {
				"foreground": "#f5e0dc"
			}
		},
		{
			"name": "entity.name.class",
			"scope": [
				"entity.name.class"
			],
			"settings": {
				"foreground": "#e0a2d3",
				"fontStyle": "bold underline"
			}
		},
		{
			"name": "entity.other.inherited-class",
			"scope": [
				"entity.other.inherited-class"
			],
			"settings": {
				"foreground": "#e0a2d3",
				"fontStyle": "bold underline"
			}
		},
		{
			"name": "support.class",
			"scope": [
				"support.class"
			],
			"settings": {
				"foreground": "#e0a2d3"
			}
		},
		{
			"name": "entity.name.type",
			"scope": [
				"entity.name.type"
			],
			"settings": {
				"foreground": "#e0a2d3"
			}
		},
		{
			"name": "support.type",
			"scope": [
				"support.type"
			],
			"settings": {
				"foreground": "#e0a2d3"
			}
		},
		{
			"name": "entity.name.tag",
			"scope": [
				"entity.name.tag"
			],
			"settings": {
				"foreground": "#e0a2d3"
			}
		},
		{
			"name": "support.class.component",
			"scope": [
				"support.class.component"
			],
			"settings": {
				"foreground": "#383d51"
			}
		},
		{
			"name": "support.class.component.jsx",
			"scope": [
				"support.class.component.jsx"
			],
			"settings": {
				"foreground": "#383d51"
			}
		},
		{
			"name": "entity.other.attribute-name",
			"scope": [
				"entity.other.attribute-name"
			],
			"settings": {
				"foreground": "#96a5b6"
			}
		},
		{
			"name": "meta.tag keyword.operator.assignment",
			"scope": [
				"meta.tag keyword.operator.assignment"
			],
			"settings": {
				"foreground": "#96a5b6"
			}
		},
		{
			"name": "meta.tag.attributes",
			"scope": [
				"meta.tag.attributes"
			],
			"settings": {
				"foreground": "#96a5b6"
			}
		},
		{
			"name": "support.type.property-name",
			"scope": [
				"support.type.property-name"
			],
			"settings": {
				"foreground": "#96a5b6"
			}
		},
		{
			"name": "support.type.property-name.css",
			"scope": [
				"support.type.property-name.css"
			],
			"settings": {
				"foreground": "#96a5b6"
			}
		},
		{
			"name": "meta.object-literal.key",
			"scope": [
				"meta.object-literal.key"
			],
			"settings": {
				"foreground": "#96a5b6"
			}
		},
		{
			"name": "variable.other.property",
			"scope": [
				"variable.other.property"
			],
			"settings": {
				"foreground": "#96a5b6"
			}
		},
		{
			"name": "list.hoverBackground",
			"scope": [
				"list.hoverBackground"
			],
			"settings": {
				"foreground": "#1c1e29cc"
			}
		},
		{
			"name": "list.hoverForeground",
			"scope": [
				"list.hoverForeground"
			],
			"settings": {
				"foreground": "#a7a4af"
			}
		},
		{
			"name": "support.type.property-name.css",
			"scope": [
				"support.type.property-name.css"
			],
			"settings": {
				"foreground": "#96a5b6"
			}
		},
		{
			"name": "meta.property-name",
			"scope": [
				"meta.property-name"
			],
			"settings": {
				"foreground": "#96a5b6"
			}
		},
		{
			"name": "support.constant.property-value",
			"scope": [
				"support.constant.property-value"
			],
			"settings": {
				"foreground": "#33b3cc"
			}
		},
		{
			"name": "constant.other.color",
			"scope": [
				"constant.other.color"
			],
			"settings": {
				"foreground": "#33b3cc"
			}
		},
		{
			"name": "meta.property-value",
			"scope": [
				"meta.property-value"
			],
			"settings": {
				"foreground": "#33b3cc"
			}
		},
		{
			"name": "meta.selector",
			"scope": [
				"meta.selector"
			],
			"settings": {
				"foreground": "#e0a2d3"
			}
		},
		{
			"name": "entity.name.tag.css",
			"scope": [
				"entity.name.tag.css"
			],
			"settings": {
				"foreground": "#e0a2d3"
			}
		},
		{
			"name": "entity.other.attribute-name.class.css",
			"scope": [
				"entity.other.attribute-name.class.css"
			],
			"settings": {
				"foreground": "#e0a2d3"
			}
		},
		{
			"name": "entity.other.attribute-name.id.css",
			"scope": [
				"entity.other.attribute-name.id.css"
			],
			"settings": {
				"foreground": "#e0a2d3"
			}
		},
		{
			"name": "punctuation",
			"scope": [
				"punctuation"
			],
			"settings": {
				"foreground": "#394060"
			}
		},
		{
			"name": "punctuation.definition",
			"scope": [
				"punctuation.definition"
			],
			"settings": {
				"foreground": "#362942"
			}
		},
		{
			"name": "punctuation.separator",
			"scope": [
				"punctuation.separator"
			],
			"settings": {
				"foreground": "#394060"
			}
		},
		{
			"name": "punctuation.terminator",
			"scope": [
				"punctuation.terminator"
			],
			"settings": {
				"foreground": "#394060"
			}
		},
		{
			"name": "punctuation.accessor",
			"scope": [
				"punctuation.accessor"
			],
			"settings": {
				"foreground": "#7a73cc"
			}
		},
		{
			"name": "punctuation.definition.tag",
			"scope": [
				"punctuation.definition.tag"
			],
			"settings": {
				"foreground": "#362942"
			}
		},
		{
			"name": "meta.brace",
			"scope": [
				"meta.brace"
			],
			"settings": {
				"foreground": "#362942"
			}
		},
		{
			"name": "meta.brace.round",
			"scope": [
				"meta.brace.round"
			],
			"settings": {
				"foreground": "#362942"
			}
		},
		{
			"name": "meta.brace.square",
			"scope": [
				"meta.brace.square"
			],
			"settings": {
				"foreground": "#362942"
			}
		},
		{
			"name": "meta.brace.curly",
			"scope": [
				"meta.brace.curly"
			],
			"settings": {
				"foreground": "#362942"
			}
		},
		{
			"name": "entity.name.function.decorator",
			"scope": [
				"entity.name.function.decorator"
			],
			"settings": {
				"foreground": "#f184bce6"
			}
		},
		{
			"name": "punctuation.definition.decorator",
			"scope": [
				"punctuation.definition.decorator"
			],
			"settings": {
				"foreground": "#f184bce6"
			}
		},
		{
			"name": "markup.heading",
			"scope": [
				"markup.heading"
			],
			"settings": {
				"foreground": "#e0a2d3",
				"fontStyle": "bold"
			}
		},
		{
			"name": "entity.name.section.markdown",
			"scope": [
				"entity.name.section.markdown"
			],
			"settings": {
				"foreground": "#e0a2d3",
				"fontStyle": "bold"
			}
		},
		{
			"name": "markup.bold",
			"scope": [
				"markup.bold"
			],
			"settings": {
				"foreground": "#afd1e9cf",
				"fontStyle": "bold"
			}
		},
		{
			"name": "markup.italic",
			"scope": [
				"markup.italic"
			],
			"settings": {
				"foreground": "#95c17b",
				"fontStyle": "italic"
			}
		},
		{
			"name": "markup.inline.raw",
			"scope": [
				"markup.inline.raw"
			],
			"settings": {
				"foreground": "#95c17b"
			}
		},
		{
			"name": "markup.fenced_code.block.markdown",
			"scope": [
				"markup.fenced_code.block.markdown"
			],
			"settings": {
				"foreground": "#95c17b"
			}
		},
		{
			"name": "markup.quote",
			"scope": [
				"markup.quote"
			],
			"settings": {
				"foreground": "#383d51",
				"fontStyle": "italic"
			}
		},
		{
			"name": "markup.underline.link",
			"scope": [
				"markup.underline.link"
			],
			"settings": {
				"foreground": "#f5e0dc",
				"fontStyle": "underline"
			}
		},
		{
			"name": "markup.inserted",
			"scope": [
				"markup.inserted"
			],
			"settings": {
				"foreground": "#449dab"
			}
		},
		{
			"name": "markup.inserted.git_gutter",
			"scope": [
				"markup.inserted.git_gutter"
			],
			"settings": {
				"foreground": "#449dab"
			}
		},
		{
			"name": "markup.changed",
			"scope": [
				"markup.changed"
			],
			"settings": {
				"foreground": "#6183bb"
			}
		},
		{
			"name": "markup.changed.git_gutter",
			"scope": [
				"markup.changed.git_gutter"
			],
			"settings": {
				"foreground": "#6183bb"
			}
		},
		{
			"name": "markup.deleted",
			"scope": [
				"markup.deleted"
			],
			"settings": {
				"foreground": "#914c54"
			}
		},
		{
			"name": "markup.deleted.git_gutter",
			"scope": [
				"markup.deleted.git_gutter"
			],
			"settings": {
				"foreground": "#914c54"
			}
		},
		{
			"name": "invalid",
			"scope": [
				"invalid"
			],
			"settings": {
				"foreground": "#FF6188"
			}
		},
		{
			"name": "invalid.illegal",
			"scope": [
				"invalid.illegal"
			],
			"settings": {
				"foreground": "#FF6188"
			}
		},
		{
			"name": "invalid.deprecated",
			"scope": [
				"invalid.deprecated"
			],
			"settings": {
				"foreground": "#383d51"
			}
		},
		{
			"name": "comment.line.todo",
			"scope": [
				"comment.line.todo"
			],
			"settings": {
				"foreground": "#f184bce6",
				"fontStyle": "bold"
			}
		},
		{
			"name": "comment.block.todo",
			"scope": [
				"comment.block.todo"
			],
			"settings": {
				"foreground": "#f184bce6",
				"fontStyle": "bold"
			}
		},
		{
			"name": "comment.line.fixme",
			"scope": [
				"comment.line.fixme"
			],
			"settings": {
				"foreground": "#ffcb6b",
				"fontStyle": "bold"
			}
		},
		{
			"name": "comment.block.fixme",
			"scope": [
				"comment.block.fixme"
			],
			"settings": {
				"foreground": "#ffcb6b",
				"fontStyle": "bold"
			}
		},
		{
			"name": "comment.line.note",
			"scope": [
				"comment.line.note"
			],
			"settings": {
				"foreground": "#78DCE8",
				"fontStyle": "bold"
			}
		},
		{
			"name": "comment.block.note",
			"scope": [
				"comment.block.note"
			],
			"settings": {
				"foreground": "#78DCE8",
				"fontStyle": "bold"
			}
		},
		{
			"name": "string.quoted.docstring",
			"scope": [
				"string.quoted.docstring"
			],
			"settings": {
				"foreground": "#383d51",
				"fontStyle": "italic"
			}
		},
		{
			"name": "string.quoted.docstring.multi.python",
			"scope": [
				"string.quoted.docstring.multi.python"
			],
			"settings": {
				"foreground": "#383d51",
				"fontStyle": "italic"
			}
		},
		{
			"name": "string.quoted.docstring.raw.multi.python",
			"scope": [
				"string.quoted.docstring.raw.multi.python"
			],
			"settings": {
				"foreground": "#383d51",
				"fontStyle": "italic"
			}
		},
		{
			"name": "source.yaml",
			"scope": [
				"source.yaml"
			],
			"settings": {
				"foreground": "#a7a4af"
			}
		},
		{
			"name": "entity.name.tag.yaml",
			"scope": [
				"entity.name.tag.yaml"
			],
			"settings": {
				"foreground": "#96a5b6"
			}
		},
		{
			"name": "string.unquoted.plain.out.yaml",
			"scope": [
				"string.unquoted.plain.out.yaml"
			],
			"settings": {
				"foreground": "#95c17b"
			}
		},
		{
			"name": "string.quoted.single.yaml",
			"scope": [
				"string.quoted.single.yaml"
			],
			"settings": {
				"foreground": "#95c17b"
			}
		},
		{
			"name": "meta.structure.dictionary.key.json",
			"scope": [
				"meta.structure.dictionary.key.json"
			],
			"settings": {
				"foreground": "#96a5b6"
			}
		},
		{
			"name": "support.type.property-name.json",
			"scope": [
				"support.type.property-name.json"
			],
			"settings": {
				"foreground": "#96a5b6"
			}
		},
		{
			"name": "meta.structure.dictionary.value.json",
			"scope": [
				"meta.structure.dictionary.value.json"
			],
			"settings": {
				"foreground": "#95c17b"
			}
		},
		{
			"name": "meta.property-list.css",
			"scope": [
				"meta.property-list.css"
			],
			"settings": {
				"foreground": "#96a5b6"
			}
		}
	],
	"semanticTokenColors": {
		"comment": "#383d51",
		"string": "#95c17b",
		"number": "#33b3cc",
		"regexp": "#FF6188",
		"keyword": "#afd1e9cf",
		"operator": "#E60063",
		"variable": "#e3e1e8c7",
		"parameter": "#8e8db3",
		"property": "#96a5b6",
		"function": "#f5e0dc",
		"method": "#f5e0dc",
		"class": "#e0a2d3",
		"interface": "#93e3db",
		"enum": "#e0a2d3",
		"enumMember": "#33b3cc",
		"type": "#e0a2d3",
		"typeParameter": "#93e3db",
		"namespace": "#f0c9dd",
		"decorator": "#f184bce6",
		"macro": "#f184bce6",
		"*.deprecated": {
			"fontStyle": "strikethrough"
		},
		"*.documentation": {
			"foreground": "#4D4A56",
			"fontStyle": "italic"
		}
	}
}